mp_procs/__init__.py
mp_procs/dproc.py
mp_procs/qproc.py
mp_procs-0.1.1.dist-info/licenses/LICENSE
mp_procs-0.1.1.dist-info/METADATA
mp_procs-0.1.1.dist-info/WHEEL
mp_procs-0.1.1.dist-info/entry_points.txt
mp_procs-0.1.1.dist-info/top_level.txt
mp_procs-0.1.1.dist-info/RECORD
