Metadata-Version: 2.4
Name: mp-procs
Version: 0.1.1
Summary: Common lightweight PyTerrier adapters for specific artifact shapes - query and document processors for modular IR pipelines
License-File: LICENSE
Requires-Dist: python-terrier
Requires-Dist: pyterrier-alpha
Dynamic: license-file
